[
  {
    "image": "thais.jpg",
    "name": "Thaís Blasio Martins",
    "title": "Municipal Education Secretary of São Paulo",
    "tags": "Education Programms"
  },
  {
    "image": "roseli.jpeg",
    "name": "Roseli de Deus Lopes",
    "title": "Instituo de Estudos Avancados | IEA-USP",
    "tags": "Vice-diretora do IEA"
  },
  {
    "image": "mensing.jpeg",
    "name": "Sven Mensing",
    "title": "Goethe-Institut São Paulo",
    "tags": "Chefe dos Serviços de Informação do Goethe-Institut América do Sul"
  },
  {
    "image": "marcio_weichert.jpeg",
    "name": "Marcio Weichert",
    "title": "DWIH São Paulo",
    "tags": "Gestor Executivo"
  }
]